Workbook

Sheet Raw Data
A1: Order ID | B1: Order Date | C1: Customer ID | D1: Customer Name | E1: Product | F1: Category | G1: Sub-Category | H1: Region | I1: City | J1: State | K1: Quantity | L1: Sales | M1: Discount | N1: Profit | O1: Payment Mode | P1: Year | Q1: Month | R1: Profit Margin | S1: Sales Category | T1: month num | W1: count of blank cells
A2: ORD0001 | B2: 45800 | C2: CUST055 | D2: Ananya Kumar | E2: Keyboard | F2: Electronics | G2: Accessories | H2: North | I2: Jaipur | J2: Rajasthan | K2: 4 | L2: 6840 | M2: 0.05 | N2: 1668.65 | O2: Net Banking | P2: =YEAR(B2) -> 2025 | Q2: =TEXT(B2,"mmm") -> May | R2: =N2/L2 -> 0.24395468 | S2: =IF(L2>=30000,"High","Low") -> Low | T2: =MONTH(B2) -> 5 | W2: =COUNTBLANK(A2:O501) -> 0
A3: ORD0002 | B3: 45991 | C3: CUST013 | D3: Rahul Rao | E3: Laptop | F3: Electronics | G3: Computers | H3: South | I3: Chennai | J3: Tamil Nadu | K3: 5 | L3: 192500 | M3: 0.3 | N3: 3071.7 | O3: Credit Card | P3: =YEAR(B3) -> 2025 | Q3: =TEXT(B3,"mmm") -> Nov | R3: =N3/L3 -> 0.015956883 | S3: =IF(L3>=30000,"High","Low") -> High | T3: =MONTH(B3) -> 11
A4: ORD0003 | B4: 45906 | C4: CUST022 | D4: Arjun Verma | E4: Office Chair | F4: Furniture | G4: Chairs | H4: North | I4: Delhi | J4: Delhi | K4: 4 | L4: 32300 | M4: 0.05 | N4: 7482.28 | O4: Credit Card | P4: =YEAR(B4) -> 2025 | Q4: =TEXT(B4,"mmm") -> Sep | R4: =N4/L4 -> 0.23164954 | S4: =IF(L4>=30000,"High","Low") -> High | T4: =MONTH(B4) -> 9
A5: ORD0004 | B5: 45857 | C5: CUST049 | D5: Neha Gupta | E5: Laptop | F5: Electronics | G5: Computers | H5: North | I5: Jaipur | J5: Rajasthan | K5: 3 | L5: 115500 | M5: 0.3 | N5: 17975.52 | O5: Net Banking | P5: =YEAR(B5) -> 2025 | Q5: =TEXT(B5,"mmm") -> Jul | R5: =N5/L5 -> 0.15563221 | S5: =IF(L5>=30000,"High","Low") -> High | T5: =MONTH(B5) -> 7
A6: ORD0005 | B6: 45755 | C6: CUST063 | D6: Varun Verma | E6: Keyboard | F6: Electronics | G6: Accessories | H6: South | I6: Chennai | J6: Tamil Nadu | K6: 3 | L6: 5130 | M6: 0.05 | N6: 1315.86 | O6: Net Banking | P6: =YEAR(B6) -> 2025 | Q6: =TEXT(B6,"mmm") -> Apr | R6: =N6/L6 -> 0.25650292 | S6: =IF(L6>=30000,"High","Low") -> Low | T6: =MONTH(B6) -> 4
A7: ORD0006 | B7: 45818 | C7: CUST008 | D7: Isha Rao | E7: Backpack | F7: Bags | G7: Travel | H7: West | I7: Mumbai | J7: Maharashtra | K7: 1 | L7: 1600 | M7: 0 | N7: 314.94 | O7: Net Banking | P7: =YEAR(B7) -> 2025 | Q7: =TEXT(B7,"mmm") -> Jun | R7: =N7/L7 -> 0.1968375 | S7: =IF(L7>=30000,"High","Low") -> Low | T7: =MONTH(B7) -> 6
A8: ORD0007 | B8: 45918 | C8: CUST021 | D8: Kavya Reddy | E8: Laptop | F8: Electronics | G8: Computers | H8: North | I8: Gurugram | J8: Haryana | K8: 1 | L8: 38500 | M8: 0.3 | N8: 482.69 | O8: Credit Card | P8: =YEAR(B8) -> 2025 | Q8: =TEXT(B8,"mmm") -> Sep | R8: =N8/L8 -> 0.012537403 | S8: =IF(L8>=30000,"High","Low") -> High | T8: =MONTH(B8) -> 9
A9: ORD0008 | B9: 45949 | C9: CUST052 | D9: Aarav Iyer | E9: Wireless Mouse | F9: Electronics | G9: Accessories | H9: North | I9: Delhi | J9: Delhi | K9: 2 | L9: 1920 | M9: 0.2 | N9: 245.63 | O9: Cash | P9: =YEAR(B9) -> 2025 | Q9: =TEXT(B9,"mmm") -> Oct | R9: =N9/L9 -> 0.12793229 | S9: =IF(L9>=30000,"High","Low") -> Low | T9: =MONTH(B9) -> 10
A10: ORD0009 | B10: 45925 | C10: CUST075 | D10: Priya Rao | E10: Notebook | F10: Stationery | G10: Office Supplies | H10: North | I10: Delhi | J10: Delhi | K10: 3 | L10: 486 | M10: 0.1 | N10: 40.31 | O10: Credit Card | P10: =YEAR(B10) -> 2025 | Q10: =TEXT(B10,"mmm") -> Sep | R10: =N10/L10 -> 0.082942387 | S10: =IF(L10>=30000,"High","Low") -> Low | T10: =MONTH(B10) -> 9
A11: ORD0010 | B11: 45725 | C11: CUST034 | D11: Rohan Kumar | E11: Office Chair | F11: Furniture | G11: Chairs | H11: West | I11: Ahmedabad | J11: Gujarat | K11: 3 | L11: 21675 | M11: 0.15 | N11: 1843.25 | O11: UPI | P11: =YEAR(B11) -> 2025 | Q11: =TEXT(B11,"mmm") -> Mar | R11: =N11/L11 -> 0.085040369 | S11: =IF(L11>=30000,"High","Low") -> Low | T11: =MONTH(B11) -> 3
A12: ORD0011 | B12: 45976 | C12: CUST002 | D12: Kavya Kumar | E12: Desk | F12: Furniture | G12: Tables | H12: South | I12: Hyderabad | J12: Telangana | K12: 5 | L12: 60000 | M12: 0 | N12: 5679.13 | O12: Debit Card | P12: =YEAR(B12) -> 2025 | Q12: =TEXT(B12,"mmm") -> Nov | R12: =N12/L12 -> 0.094652167 | S12: =IF(L12>=30000,"High","Low") -> High | T12: =MONTH(B12) -> 11
A13: ORD0012 | B13: 45836 | C13: CUST017 | D13: Rahul Gupta | E13: USB Cable | F13: Electronics | G13: Accessories | H13: West | I13: Pune | J13: Maharashtra | K13: 1 | L13: 427.5 | M13: 0.05 | N13: 60.68 | O13: Net Banking | P13: =YEAR(B13) -> 2025 | Q13: =TEXT(B13,"mmm") -> Jun | R13: =N13/L13 -> 0.14194152 | S13: =IF(L13>=30000,"High","Low") -> Low | T13: =MONTH(B13) -> 6
A14: ORD0013 | B14: 45992 | C14: CUST039 | D14: Ananya Reddy | E14: Notebook | F14: Stationery | G14: Office Supplies | H14: South | I14: Hyderabad | J14: Telangana | K14: 5 | L14: 900 | M14: 0 | N14: 192.22 | O14: UPI | P14: =YEAR(B14) -> 2025 | Q14: =TEXT(B14,"mmm") -> Dec | R14: =N14/L14 -> 0.21357778 | S14: =IF(L14>=30000,"High","Low") -> Low | T14: =MONTH(B14) -> 12
... A501: ORD0500 | B501: 45889 | C501: CUST008 | D501: Isha Rao | E501: Laptop | F501: Electronics | G501: Computers | H501: West | I501: Mumbai | J501: Maharashtra | K501: 3 | L501: 156750 | M501: 0.05 | N501: 34505.55 | O501: Credit Card | P501: =YEAR(B501) -> 2025 | Q501: =TEXT(B501,"mmm") -> Aug | R501: =N501/L501 -> 0.2201311 | S501: =IF(L501>=30000,"High","Low") -> High | T501: =MONTH(B501) -> 8

Sheet KPI
A1: E-COMMERCE SALES & PROFITABILITY ANALYSIS
A2: KEY PERFORMANCE INDICATORS
A3: KPI | B3: VALUE
A4: Total Orders | B4: =COUNTA('Raw Data'!A2:A501) -> 500
A5: Total Sales | B5: =SUM('Raw Data'!L2:L501) -> 12242727
A6: Total Profit | B6: =SUM('Raw Data'!N2:N501) -> 1600305.3
A7: Total Quantity | B7: =SUM('Raw Data'!K2:K501) -> 1500
A8: Average Order value | B8: =B5/B4 -> 24485.454

Sheet Pivot Analysis
A3: Category | B3: Sum of Sales | C3: Sum of Profit | D3: Sum of Quantity
A4: Bags | B4: 166910 | C4: 26167.77 | D4: 169
A5: Electronics | B5: 9668092.5 | C5: 1237117.2 | D5: 809
A6: Furniture | B6: 2367150 | C6: 331603.09 | D6: 306
A7: Stationery | B7: 40574.5 | C7: 5417.2 | D7: 216
A8: Grand Total | B8: 12242727 | C8: 1600305.3 | D8: 1500
A14: Category | B14: Sum of Sales
A15: Bags | B15: 166910
A16: Electronics | B16: 9668092.5
A17: Furniture | B17: 2367150
A18: Stationery | B18: 40574.5
A19: Grand Total | B19: 12242727
A25: Category | B25: Sum of Profit
A26: Bags | B26: 26167.77
A27: Electronics | B27: 1237117.2
A28: Furniture | B28: 331603.09
A29: Stationery | B29: 5417.2
A30: Grand Total | B30: 1600305.3

Sheet Monthly Analysis
A3: Row Labels | B3: Sum of Sales | C3: Sum of Profit
A4: Jan | B4: 872796 | C4: 95731.72
A5: Feb | B5: 1480565 | C5: 251660.67
A6: Mar | B6: 1259430.5 | C6: 151695.07
A7: Apr | B7: 1004431.5 | C7: 119306.82
A8: May | B8: 658683 | C8: 76515.93
A9: Jun | B9: 488435 | C9: 78331.02
A10: Jul | B10: 1069815.5 | C10: 139223.37
A11: Aug | B11: 989842.5 | C11: 121963.71
A12: Sep | B12: 873416 | C12: 113340.82
A13: Oct | B13: 852975 | C13: 145059.85
A14: Nov | B14: 974053 | C14: 116052.69
A15: Dec | B15: 1718284 | C15: 191423.6
A16: Grand Total | B16: 12242727 | C16: 1600305.3

Sheet Product Performance
A3: Row Labels | B3: Sum of Quantity | C3: Sum of Sales | D3: Sum of Profit
A4: Laptop | B4: 107 | C4: 4889500 | D4: 614147.33
A5: Smartphone | B5: 88 | C5: 2125200 | D5: 259962.36
A6: Desk | B6: 102 | C6: 1080000 | D6: 158824.58
A7: Monitor | B7: 91 | C7: 1083150 | D7: 149610.92
A8: Printer | B8: 92 | C8: 905050 | D8: 126077.84
A9: Office Chair | B9: 100 | C9: 705075 | D9: 90272.98
A10: Bookshelf | B10: 104 | C10: 582075 | D10: 82505.53
A11: Headphones | B11: 117 | C11: 304960 | D11: 37100.36
A12: Keyboard | B12: 152 | C12: 230040 | D12: 32108.97
A13: Backpack | B13: 79 | C13: 113360 | D13: 18315.4
A14: Wireless Mouse | B14: 105 | C14: 108300 | D14: 14928.39
A15: Water Bottle | B15: 90 | C15: 53550 | D15: 7852.37
... A19: Grand Total | B19: 1500 | C19: 12242727 | D19: 1600305.3
A23: Product | B23: Sum of Profit
A24: Laptop | B24: 614147.33
A25: Smartphone | B25: 259962.36
A26: Desk | B26: 158824.58
A27: Monitor | B27: 149610.92
A28: Printer | B28: 126077.84
A29: Grand Total | B29: 1308623

Sheet Region Performance
A3: Region | B3: Sum of Quantity | C3: Sum of Sales | D3: Sum of Profit
A4: East | B4: 138 | C4: 920017.5 | D4: 136373.34
A5: North | B5: 440 | C5: 3325548.5 | D5: 445703.86
A6: South | B6: 507 | C6: 4348148.5 | D6: 538638.26
A7: West | B7: 415 | C7: 3649012.5 | D7: 479589.81
A8: Grand Total | B8: 1500 | C8: 12242727 | D8: 1600305.3
A12: Region | B12: Sum of Sales
A13: East | B13: 920017.5
A14: North | B14: 3325548.5
A15: South | B15: 4348148.5
A16: West | B16: 3649012.5
A17: Grand Total | B17: 12242727

Sheet Payment Mode Analysis
A3: Row Labels | B3: Sum of Quantity | C3: Sum of Sales | D3: Sum of Profit
A4: Cash | B4: 343 | C4: 2215332.5 | D4: 305693.48
A5: Credit Card | B5: 285 | C5: 3352691 | D5: 486248.08
A6: Debit Card | B6: 305 | C6: 2764999 | D6: 325667.42
A7: Net Banking | B7: 277 | C7: 1954657.5 | D7: 240645.44
A8: UPI | B8: 290 | C8: 1955047 | D8: 242050.85
A9: Grand Total | B9: 1500 | C9: 12242727 | D9: 1600305.3

Sheet Discount Analysis
A3: Discount | B3: Sum of Sales | C3: Sum of Quantity | D3: Sum of Profit
A4: 0 | B4: 2458490 | C4: 239 | D4: 423679.89
A5: 0.05 | B5: 1788204 | C5: 181 | D5: 266877.87
A6: 0.1 | B6: 1270044 | C6: 210 | D6: 175869.13
A7: 0.15 | B7: 1031016 | C7: 192 | D7: 126771.59
A8: 0.2 | B8: 2650416 | C8: 257 | D8: 330296.92
A9: 0.25 | B9: 1194765 | C9: 189 | D9: 129150.92
A10: 0.3 | B10: 1849792 | C10: 232 | D10: 147658.95
A11: Grand Total | B11: 12242727 | C11: 1500 | D11: 1600305.3
A16: Discount | B16: Sum of Profit
A17: 0 | B17: 423679.89
A18: 0.05 | B18: 266877.87
A19: 0.1 | B19: 175869.13
A20: 0.15 | B20: 126771.59
A21: 0.2 | B21: 330296.92
A22: 0.25 | B22: 129150.92
A23: 0.3 | B23: 147658.95
A24: Grand Total | B24: 1600305.3

Sheet Dashboard
A1: E-COMMERCE SALES & PROFITABILITY DASHBOARD
A4: TOTAL ORDERS | D4: TOTAL SALES | G4: TOTAL PROFIT | J4: TOTAL QUANTITY | M4: AVERAGE ORDER VALUE
A6: =KPI!B4 -> 500 | D6: =KPI!B5 -> 12242727 | G6: =KPI!B6 -> 1600305.3 | J6: =KPI!B7 -> 1500 | M6: =KPI!B8 -> 24485.454

Sheet Key Insights
A1: KEY BUSINESS INSIGHTS
A3: Area | B3: Key Insight
A4: Overall Performance | B4: The business recorded 500 orders, generating total sales of ₹1.22 crore and total profit of approximately ₹16.00 lakh.
A5: Category | B5: Electronics generated the highest sales (₹96.68 lakh) and the highest total profit (₹12.37 lakh) among the categories.
A6: Monthly Trend | B6: December recorded the highest monthly sales at approximately ₹17.18 lakh, while June recorded the lowest at approximately ₹4.88 lakh.
A7: Region | B7: South recorded the highest regional sales at approximately ₹43.48 lakh, followed by West and North.
A8: Product | B8: Laptop generated the highest product-level profit at approximately ₹6.14 lakh, followed by Smartphone at approximately ₹2.60 lakh.
A9: Payment Mode | B9: Credit Card transactions generated the highest sales among the payment modes, at approximately ₹33.53 lakh.
A10: Discount | B10: Total profit varied across discount levels, with the 0% discount group recording the highest total profit in this dataset.
A12: PROJECT OBJECTIVE
A13: To analyze e-commerce sales and profitability, identify key performance trends, and present actionable business insights through an Excel dashboard.
A15: TOOLS & TECHNIQUES
A16: Excel | Data Cleaning | PivotTables | PivotCharts | Data Analysis | Dashboarding
